flotech/Ansari_1994.py
flotech/AzizandGovier1972.py
flotech/BHPExample.py
flotech/BeggsandBrill.py
flotech/DB_Example.py
flotech/DunsandRos1963.py
flotech/FancherandBrown1963.py
flotech/FluidProps.py
flotech/GasProp.py
flotech/Gray1974.py
flotech/HYDRO3Phase.py
flotech/Hagendornandbrown.py
flotech/MukherjeeandBrill1985.py
flotech/OilProps.py
flotech/Solving_Intersections.py
flotech/Stanford.py
flotech/Vogel.py
flotech/WaterProps.py
flotech/__init__.py
flotech/test.py
flotech-0.2.2.dist-info/METADATA
flotech-0.2.2.dist-info/WHEEL
flotech-0.2.2.dist-info/top_level.txt
flotech-0.2.2.dist-info/RECORD
