Metadata-Version: 2.1
Name: flotech
Version: 0.2.2
Summary: Multiphase flow package [This is a Test Release]
Home-page: https://github.com/Nashat90/flotech
Author: Nashat Jumaah Omar
Author-email: nashattt90@gmail.com
Classifier: Programming Language :: Python :: 3
Classifier: License :: OSI Approved :: MIT License
Classifier: Operating System :: OS Independent
